tutkia/__init__.py
tutkia/__main__.py
tutkia/api.py
tutkia/cli.py
tutkia/config.py
tutkia/query.py
tutkia/report.py
tutkia-2023.2.18.dist-info/LICENSE
tutkia-2023.2.18.dist-info/METADATA
tutkia-2023.2.18.dist-info/WHEEL
tutkia-2023.2.18.dist-info/entry_points.txt
tutkia-2023.2.18.dist-info/top_level.txt
tutkia-2023.2.18.dist-info/RECORD
